projen_practical_constructs/__init__.py
projen_practical_constructs/py.typed
projen_practical_constructs/_jsii/__init__.py
projen_practical_constructs/_jsii/projen-practical-constructs@0.4.5.jsii.tgz
projen_practical_constructs-0.4.5.dist-info/LICENSE
projen_practical_constructs-0.4.5.dist-info/METADATA
projen_practical_constructs-0.4.5.dist-info/WHEEL
projen_practical_constructs-0.4.5.dist-info/top_level.txt
projen_practical_constructs-0.4.5.dist-info/RECORD
