Metadata-Version: 2.1
Name: projen_practical_constructs
Version: 0.4.5
Summary: Constructs and utilities for managing projects (Python, NodeJS etc) with Projen enforcing solid build, test and linting structures
Home-page: https://github.com/flaviostutz/projen-practical-constructs.git
Author: Flavio Stutz<flaviostutz@gmail.com>
License: MIT
Project-URL: Source, https://github.com/flaviostutz/projen-practical-constructs.git
Classifier: Intended Audience :: Developers
Classifier: Operating System :: OS Independent
Classifier: Programming Language :: JavaScript
Classifier: Programming Language :: Python :: 3 :: Only
Classifier: Programming Language :: Python :: 3.8
Classifier: Programming Language :: Python :: 3.9
Classifier: Programming Language :: Python :: 3.10
Classifier: Programming Language :: Python :: 3.11
Classifier: Typing :: Typed
Classifier: Development Status :: 5 - Production/Stable
Classifier: License :: OSI Approved
Requires-Python: ~=3.8
License-File: LICENSE
Requires-Dist: constructs<11.0.0,>=10.4.2
Requires-Dist: jsii<2.0.0,>=1.106.0
Requires-Dist: projen<0.92.0,>=0.91.13
Requires-Dist: publication>=0.0.3
Requires-Dist: typeguard<4.3.0,>=2.13.3
